cubicweb_oauth2/__init__.py
cubicweb_oauth2/__pkginfo__.py
cubicweb_oauth2/auth.py
cubicweb_oauth2/site_cubicweb.py
cubicweb_oauth2/views.py
cubicweb_oauth2/i18n/en.po
cubicweb_oauth2/i18n/es.po
cubicweb_oauth2/i18n/fr.po
cubicweb_oauth2-1.2.1.dist-info/METADATA
cubicweb_oauth2-1.2.1.dist-info/WHEEL
cubicweb_oauth2-1.2.1.dist-info/entry_points.txt
cubicweb_oauth2-1.2.1.dist-info/top_level.txt
cubicweb_oauth2-1.2.1.dist-info/RECORD
