Metadata-Version: 2.4
Name: cubicweb-oauth2
Version: 1.2.1
Summary: Oauth2/OpenID authentication for CubicWeb
Author-email: Logilab <contact@logilab.fr>
License: GNU Lesser General Public License v2 or later (LGPLv2+)
Project-URL: Issues, https://forge.extranet.logilab.fr/cubicweb/cubes/oauth2/-/issues
Project-URL: Repository, https://forge.extranet.logilab.fr/cubicweb/cubes/oauth2
Classifier: Environment :: Web Environment
Classifier: Framework :: CubicWeb
Classifier: Programming Language :: Python
Classifier: Programming Language :: Python :: 3
Classifier: Programming Language :: Python :: 3 :: Only
Classifier: Programming Language :: JavaScript
Requires-Python: >=3.11
Requires-Dist: cubicweb<6.0.0,>=4.5.0
Requires-Dist: authlib<2.0.0,>=1.5.2
Requires-Dist: requests<3.0.0,>=2.32.3
